LICENSE
README.md
requirements.txt
setup.py
ai4f/__init__.py
ai4f/models.py
ai4f/proxies.py
ai4f/typing.py
ai4f.egg-info/PKG-INFO
ai4f.egg-info/SOURCES.txt
ai4f.egg-info/dependency_links.txt
ai4f.egg-info/requires.txt
ai4f.egg-info/top_level.txt
ai4f/Provider/AItianhu.py
ai4f/Provider/Acytoo.py
ai4f/Provider/AiService.py
ai4f/Provider/Aichat.py
ai4f/Provider/Ails.py
ai4f/Provider/Bard.py
ai4f/Provider/Bing.py
ai4f/Provider/Bing_Sydney.py
ai4f/Provider/ChatgptAi.py
ai4f/Provider/ChatgptLogin.py
ai4f/Provider/DeepAi.py
ai4f/Provider/DfeHub.py
ai4f/Provider/EasyChat.py
ai4f/Provider/Equing.py
ai4f/Provider/FastGpt.py
ai4f/Provider/Forefront.py
ai4f/Provider/GetGpt.py
ai4f/Provider/H2o.py
ai4f/Provider/Liaobots.py
ai4f/Provider/Lockchat.py
ai4f/Provider/Opchatgpts.py
ai4f/Provider/Poe.py
ai4f/Provider/Raycast.py
ai4f/Provider/Theb.py
ai4f/Provider/V50.py
ai4f/Provider/Vercel.py
ai4f/Provider/Wewordle.py
ai4f/Provider/You.py
ai4f/Provider/Yqcloud.py
ai4f/Provider/__init__.py
ai4f/Provider/base_provider.py