Metadata-Version: 2.1
Name: ai4f
Version: 0.1.8
Summary: The AI 4 Free repository | Collection of LLMs | Forked from xtekky
Author: ZorenX
Author-email: <hansfzlorenzana@gmail.com>
Keywords: python,chatbot,reverse-engineering,openai,chatbots,gpt,language-model,gpt-3,gpt3,openai-api,gpt-4,gpt4,chatgpt,chatgpt-api,openai-chatgpt,chatgpt-free,chatgpt-4,chatgpt4,chatgpt4-api,free,free-gpt,gpt4free,g4f,ai4f,llm
Classifier: Development Status :: 2 - Pre-Alpha
Classifier: Intended Audience :: Developers
Classifier: Programming Language :: Python :: 3
Classifier: Operating System :: Unix
Classifier: Operating System :: MacOS :: MacOS X
Classifier: Operating System :: Microsoft :: Windows
License-File: LICENSE
